MANIFEST.in
README.rst
requirements.txt
setup.cfg
setup.py
sequana_downsampling.egg-info/PKG-INFO
sequana_downsampling.egg-info/SOURCES.txt
sequana_downsampling.egg-info/dependency_links.txt
sequana_downsampling.egg-info/entry_points.txt
sequana_downsampling.egg-info/not-zip-safe
sequana_downsampling.egg-info/requires.txt
sequana_downsampling.egg-info/top_level.txt
sequana_pipelines/downsampling/__init__.py
sequana_pipelines/downsampling/config.yaml
sequana_pipelines/downsampling/downsampling.rules
sequana_pipelines/downsampling/main.py
sequana_pipelines/downsampling/requirements.txt
sequana_pipelines/downsampling/schema.yaml