Metadata-Version: 1.2
Name: sequana-downsampling
Version: 0.9.0
Summary: downsample NGS data sets
Home-page: https://github.com/sequana/
Author: thomas cokelaer
Author-email: thomas.cokelaer@pasteur.fr
Maintainer: thomas cokelaer
Maintainer-email: thomas.cokelaer@pasteur.fr
License: new BSD
Keywords: NGS, sequana, snakemake, fastq, downsampling
Platform: Linux
Platform: Unix
Platform: MacOsX
Platform: Windows
Classifier: Development Status :: 5 - Production/Stable
Classifier: Intended Audience :: Education
Classifier: Intended Audience :: End Users/Desktop
Classifier: Intended Audience :: Science/Research
Classifier: License :: OSI Approved :: BSD License
Classifier: Operating System :: OS Independent
Classifier: Programming Language :: Python :: 3.7
Classifier: Programming Language :: Python :: 3.8
Classifier: Programming Language :: Python :: 3.9
Classifier: Topic :: Software Development :: Libraries :: Python Modules
Classifier: Topic :: Scientific/Engineering :: Bio-Informatics
Classifier: Topic :: Scientific/Engineering :: Information Analysis
Classifier: Topic :: Scientific/Engineering :: Mathematics
Classifier: Topic :: Scientific/Engineering :: Physics
